{"assets/Bumho-nisubire.pdf":["assets/Bumho-nisubire.pdf"],"assets/blender.svg":["assets/blender.svg"],"assets/cnn_ml.png":["assets/cnn_ml.png"],"assets/coursera.png":["assets/coursera.png"],"assets/django.svg":["assets/django.svg"],"assets/dotnet.svg":["assets/dotnet.svg"],"assets/eventend.png":["assets/eventend.png"],"assets/expo.svg":["assets/expo.svg"],"assets/face.png":["assets/face.png"],"assets/ffwpu.png":["assets/ffwpu.png"],"assets/figma.svg":["assets/figma.svg"],"assets/findMe.png":["assets/findMe.png"],"assets/flutter.svg":["assets/flutter.svg"],"assets/github.svg":["assets/github.svg"],"assets/javascript.svg":["assets/javascript.svg"],"assets/linkedin.svg":["assets/linkedin.svg"],"assets/mmu.png":["assets/mmu.png"],"assets/node.png":["assets/node.png"],"assets/nodejs.svg":["assets/nodejs.svg"],"assets/photoshop.svg":["assets/photoshop.svg"],"assets/pinterest.svg":["assets/pinterest.svg"],"assets/profile.png":["assets/profile.png"],"assets/project.png":["assets/project.png"],"assets/python.svg":["assets/python.svg"],"assets/react.svg":["assets/react.svg"],"assets/status.png":["assets/status.png"],"assets/tensorflow.svg":["assets/tensorflow.svg"],"assets/twitter.svg":["assets/twitter.svg"],"assets/yetublog.png":["assets/yetublog.png"],"packages/cupertino_icons/assets/CupertinoIcons.ttf":["packages/cupertino_icons/assets/CupertinoIcons.ttf"]}